[
    {
        "username": "romain",
        "password": "monmotdepasse",
        "type": "a1VD1V3B7LhQ",
        "manage": [
            7,
            9
        ]
    },
    {
        "username": "ExampleRH",
        "password": "monpassword",
        "type": "QOHarkKCWiNF"
    },
    {
        "username": "manage2",
        "password": "apassword2",
        "type": "1R12gjkt4gMo"
    },
    {
        "username": "Momo",
        "password": "salam",
        "type": "1R12gjkt4gMo"
    },
    {
        "username": "saliut",
        "password": "cependant",
        "type": "1R12gjkt4gMo"
    },
    {
        "username": "Sammy",
        "password": "hello",
        "type": "1R12gjkt4gMo"
    },
    {
        "username": "Luc",
        "password": "Skywalk",
        "type": "1R12gjkt4gMo"
    }
]